faal/__init__.py
faal/_nbdev.py
faal/hafez.py
faal-1.0.1.dist-info/LICENSE
faal-1.0.1.dist-info/METADATA
faal-1.0.1.dist-info/WHEEL
faal-1.0.1.dist-info/entry_points.txt
faal-1.0.1.dist-info/top_level.txt
faal-1.0.1.dist-info/RECORD
